mpl_multitab/__init__.py
mpl_multitab/_logging.py
mpl_multitab/core.py
mpl_multitab/examples/_1d.py
mpl_multitab/examples/_2d.py
mpl_multitab/examples/_3d.py
mpl_multitab/examples/__init__.py
mpl_multitab-1.2.0.dist-info/LICENSE
mpl_multitab-1.2.0.dist-info/METADATA
mpl_multitab-1.2.0.dist-info/WHEEL
mpl_multitab-1.2.0.dist-info/top_level.txt
mpl_multitab-1.2.0.dist-info/RECORD
