Metadata-Version: 2.1
Name: mpl-multitab
Version: 1.2.0
Summary: Tabbed figure manager for matplotlib using pyQt
Author-email: Hannes Breytenbach <hannes@saao.ac.za>
License: MIT
Project-URL: Homepage, https://github.com/astromancer/mpl-multitab
Project-URL: Bug Tracker, https://github.com/astromancer/mpl-multitab/issues
Classifier: Development Status :: 4 - Beta
Classifier: Intended Audience :: Science/Research
Classifier: Intended Audience :: Education
Classifier: Programming Language :: Python :: 3.8
Classifier: License :: OSI Approved :: MIT License
Classifier: Operating System :: POSIX :: Linux
Requires-Python: >=3.8
License-File: LICENSE
Provides-Extra: tests
Requires-Dist: pytest ; extra == 'tests'
Requires-Dist: pytest-qt ; extra == 'tests'
